{
  "id": "topic_5416700",
  "title": "NAMX Coin",
  "author": "NAMX Coin",
  "created_time": "October 11, 2022, 07:44:49 AM",
  "content": "We aim to connect buyers and sellers and liberate water sales for a truly free and competitive market. We can do it together. We can do it with NAMX!Learn more atWebsite: http://namx.io/Whitepaper: http://namx.io/wp-content/uploads/2022/THE-NAMX.pdf",
  "score": 0,
  "upvotes": 0,
  "downvotes": 0,
  "url": "https://bitcointalk.org/index.php?topic=5416700",
  "comments": []
}