{
  "id": "topic_5419733",
  "title": "betnomi",
  "author": "betnomi",
  "created_time": "November 07, 2022, 12:20:03 PMLast edit: November 14, 2022, 11:18:49 AM by betnomi",
  "content": "Guys, it's me again! This is the third round of 6 due to which the custom cold wallet will find its new owner. I took into account your wishes and now, starting from this round, we will have a lot of slots (please let me know if the raffle rules need to be improved). Good luck!Free shipping!I will announce the block number when we are full.Inactive not acceptedYour forum account must be registered no later than September 1 of the current year.How this will work:Choose a number between 00 - 99 (no random)After I choose a block, the last symbol of the hash will determine the winner.00 - rat03gopoh01 - Streissi02 - GazetaBitcoin03 - Little Mouse04 - xandry05 - 5tift06 - TopTort77707 - krogoth08 - Steeley09 - Real-Duke10 - QuakerBull11 - TheCryptoKid12 - Hotdog713 - Stackinsats77714 - Danydee15 -16 - wwzsocki17 -18 - notblox119 - Mbitr20 - mx12.levins21 - Rémi Forte22 - tread9323 - 24 - famososMuertos25 - bullrun2020bro26 -27 -28 - bct_ail29 - Ryu_Ar130 -31 - montreal132 -33 - Heisenberg34 - CryptoYar35 - buckrogers36 - PawGo37 - Dernoste38 - -doubleU-39 - Pmalek40 - Harkorede41 - mocacinno42 - tweetious43 - cygan44 - naira45 - pinky123446 - NeuroticFish47 - Iroh48 - Koal-8449 - nara189250 - minerjones51 - Ratimov52 - aoluain53 - Becassine54 - PeakDK55 - lokas050656 - 2stout57 -58 -59 - Rizzrack60 - LTU_btc61 - PreciousMetapsICT62 -63 - bitbollo64 - HeRetiK65 -66 - Thiago00767 -68 - Remsjack69 - hookzup170 - Markzellers71 - owlcatz72 - please73 - ovcijisir74 - Willi997475 -76 - MoparMiningLLC77 - Amax1678 - WhyFhy79 - Darker4580 - YodasRedRocket81 - bestcoin_5982 - CoinageMint83 - haloxon84 - sunnybwoy85 - Inwestour86 - examplens87 - Krytowerk88 - Buchi-8889 -90 - delfastTions91 - Fundamentals92 - salad daging93 -94 -95 - BRINIRHA96 -97 - Doblezero98 -99 - JanEmilThis is the 3 round out of 6, and I can say with confidence that the winner of the first round was satisfied!Quote from: MoparMiningLLC on November 01, 2022, 03:01:20 PMArrived today! thanks!Additional photos:Quote",
  "score": 0,
  "upvotes": 0,
  "downvotes": 0,
  "url": "https://bitcointalk.org/index.php?topic=5419733",
  "comments": [
    {
      "author": "QuakerBull",
      "created_time": "November 07, 2022, 12:21:20 PM",
      "body": "10, please ty",
      "score": 0,
      "upvotes": 0,
      "downvotes": 0
    },
    {
      "author": "krogoth",
      "created_time": "November 07, 2022, 12:23:51 PM",
      "body": "7 thanks",
      "score": 0,
      "upvotes": 0,
      "downvotes": 0
    },
    {
      "author": "NeuroticFish",
      "created_time": "November 07, 2022, 12:24:00 PM",
      "body": "46 - NeuroticFishThank you!",
      "score": 0,
      "upvotes": 0,
      "downvotes": 0
    },
    {
      "author": "rat03gopoh",
      "created_time": "November 07, 2022, 12:25:54 PM",
      "body": "00 - rat03gopohpls n ty",
      "score": 0,
      "upvotes": 0,
      "downvotes": 0
    },
    {
      "author": "Remsjack",
      "created_time": "November 07, 2022, 12:29:55 PM",
      "body": "68 - Remsjack, please!",
      "score": 0,
      "upvotes": 0,
      "downvotes": 0
    },
    {
      "author": "Amax16",
      "created_time": "November 07, 2022, 12:32:43 PM",
      "body": "77 -Amax16Thank you!",
      "score": 0,
      "upvotes": 0,
      "downvotes": 0
    },
    {
      "author": "cygan",
      "created_time": "November 07, 2022, 12:36:45 PM",
      "body": "43 - cyganbig thanks",
      "score": 0,
      "upvotes": 0,
      "downvotes": 0
    },
    {
      "author": "JanEmil",
      "created_time": "November 07, 2022, 12:41:20 PM",
      "body": "JanEmil - 99",
      "score": 0,
      "upvotes": 0,
      "downvotes": 0
    },
    {
      "author": "Rizzrack",
      "created_time": "November 07, 2022, 12:42:21 PM",
      "body": "59 - RizzrackThanks !",
      "score": 0,
      "upvotes": 0,
      "downvotes": 0
    },
    {
      "author": "willi9974",
      "created_time": "November 07, 2022, 12:43:30 PM",
      "body": "Willi9974 for the 74 please and thanks for the cool free raffle...A cold wallet more is better as one less One merit send!Best regards from germanyWilli",
      "score": 0,
      "upvotes": 0,
      "downvotes": 0
    },
    {
      "author": "tweetious",
      "created_time": "November 07, 2022, 12:43:42 PM",
      "body": "42 - tweetiousThank you !!!",
      "score": 0,
      "upvotes": 0,
      "downvotes": 0
    },
    {
      "author": "Harkorede",
      "created_time": "November 07, 2022, 12:43:54 PM",
      "body": "Harkorede - 40Thanks",
      "score": 0,
      "upvotes": 0,
      "downvotes": 0
    },
    {
      "author": "stackinsats777",
      "created_time": "November 07, 2022, 12:47:17 PMLast edit: November 08, 2022, 12:15:50 AM by stackinsats777",
      "body": "Stackinsats777 - 13 please and thanks!!Apparently I forgot how to read today. 13 is open as my account is too new per the rules of the raffle. Sorry for any confusion",
      "score": 0,
      "upvotes": 0,
      "downvotes": 0
    },
    {
      "author": "5tift",
      "created_time": "November 07, 2022, 12:56:09 PM",
      "body": "05 - 5tiftThanks",
      "score": 0,
      "upvotes": 0,
      "downvotes": 0
    },
    {
      "author": "doblezero",
      "created_time": "November 07, 2022, 01:03:42 PM",
      "body": "97- DoblezeroThanks",
      "score": 0,
      "upvotes": 0,
      "downvotes": 0
    },
    {
      "author": "Buchi-88",
      "created_time": "November 07, 2022, 01:09:01 PM",
      "body": "#88 - Buchi-88Thank you for this cool raffle",
      "score": 0,
      "upvotes": 0,
      "downvotes": 0
    },
    {
      "author": "Dernoste",
      "created_time": "November 07, 2022, 01:23:32 PM",
      "body": "37 - Dernostethank you!",
      "score": 0,
      "upvotes": 0,
      "downvotes": 0
    },
    {
      "author": "Real-Duke",
      "created_time": "November 07, 2022, 01:25:00 PM",
      "body": "09 - Real-DukeMany thanks",
      "score": 0,
      "upvotes": 0,
      "downvotes": 0
    },
    {
      "author": "Koal-84",
      "created_time": "November 07, 2022, 01:32:11 PM",
      "body": "48 - Koal-84Thanks",
      "score": 0,
      "upvotes": 0,
      "downvotes": 0
    }
  ]
}