{
  "id": "topic_5414753",
  "title": "akaros",
  "author": "akaros",
  "created_time": "September 24, 2022, 03:22:23 PM",
  "content": "Hi guys, I have some S17+ 70TH in very good conditions (30pcs selected from 100pcs) for sale.Possible to transport in SLOVAKIA a CZECHIA to your doors. You can check and test before buy. I can sell very cheap, price depends on how much pieces you want to buy. Please feel free to ask by email samo@ctr.sk",
  "score": 0,
  "upvotes": 0,
  "downvotes": 0,
  "url": "https://bitcointalk.org/index.php?topic=5414753",
  "comments": [
    {
      "author": "lowbander801",
      "created_time": "October 07, 2022, 06:23:44 AM",
      "body": "always put price",
      "score": 0,
      "upvotes": 0,
      "downvotes": 0
    },
    {
      "author": "tutorialevideo",
      "created_time": "October 20, 2022, 04:44:45 PM",
      "body": "Quote from: lowbander801 on October 07, 2022, 06:23:44 AMalways put price Price and if you accept escrow!TY",
      "score": 0,
      "upvotes": 0,
      "downvotes": 0
    }
  ]
}