{
  "id": "topic_5399303",
  "title": "HYVE",
  "author": "HYVE",
  "created_time": "May 19, 2022, 06:59:51 AM",
  "content": "It's time for a new token integration!This time we're introducing two new payment options: $FRM and $FRMx!Ferrum Network will also use the HYVE platform for their hiring process.    Read more here👇https://latest.hyve.works/dual-token-integration-frm-frmx/",
  "score": 0,
  "upvotes": 0,
  "downvotes": 0,
  "url": "https://bitcointalk.org/index.php?topic=5399303",
  "comments": []
}