{
  "id": "topic_5415416",
  "title": "1miau",
  "author": "1miau",
  "created_time": "September 29, 2022, 10:06:18 PMLast edit: January 10, 2023, 12:11:23 AM by 1miau",
  "content": "Gesponsort von Betnomi, 1miau und GazetaBitcoin. Danke auch an icopress für den Deal.  Die 9 Gewinner sind ermittelt, siehe hier. Zudem gibt bullrun2020bro als Gewinner des Hardwarewallets seinen Preis an Interessenten ab: Quote from: bullrun2020bro on January 06, 2023, 02:53:21 PMGenauso natürlich wie meine gewonnen Betnomi-Ledger-Wallets. Ich habe jetzt zwei Betnomi-Ledger bei minerjones liegen. Wenn jemand keinen Ledger besitzt und günstig bzw. gegen eine kleine Aufwandsentschädigung an einen Ledger kommen möchte, könnt ihr mir gerne ein PN schreiben. Dann veranlasse ich den Versand an euch. Wie icopress bereits in anderen Gewinnspiel angekündigt hat, wird es ein Hardware-Wallet für den Gewinner des dortigen Gewinnspiels geben und ein weiteres Hardware-Wallet wird unter allen Teilnehmern verlost: Quote from: icopress on August 31, 2022, 11:16:11 PMDarüber hinaus erhält der Gewinner mit einer Wahrscheinlichkeit von 99 % auch eine personalisierte Geldbörse!Und noch eins davon wird unter den Teilnehmern verlost! Sie sind brandneu versiegelt in der Box direkt ab Werk. QuoteDa eine zufällige Verlosung unter allen Teilnehmern eine gewisse Problematik darstellt, da ich z.B. die Teilnehmer bei Erraten der letzten beiden Ziffern (0-99) eines Block-Hashs selbst vorab zuteilen müsste und damit ins Geschehen eingreifen würde (durch das manuelle Zulosen vorab), wird der Gewinner in einem neuen Gewinnspiel ermittelt, bei dem es darum geht, die beiden Ziffern des letzten Blocks im Jahre 2022 zu erraten. Da einige Nutzer die Frist verpasst hatten, ist dieses Gewinnspiel nicht nur exklusiv für Teilnehmer des bisherigen Gewinnspiels. Relevant sind die letzten beiden Ziffern des Block-Hashs (00-99) aus dem Gewinnspiel [Gewinnspiel] Welches ist der letzte Block dieses Jahr? - gesponsort von BetnomiKann mit diesem Block kein Gewinner ermittelt werden, ist der nächste Block relevant usw...Die weiteren Regeln: Das wertvolle BTC des Gewinnspiels (0,5m BTC) wird von mir (1miau) bereitgestellt. Die Hardwarewallet wird von Betnomi bereitgestellt und der Gewinner bekommt den Gewinn von Betnomi direkt zugesandt, dazu bitte bei Gewinn eine PM inkl. Zieladresse an betnomi. Nach Rückmeldung von betnomi wird minerjones den Versand übernehmen, dazu bitte nach Gewinn minerjones eine Nachricht senden. Ich werde ihm dann ebenfalls bestätigen, wer gewonnen hat.  GazetaBitcoin tritt als Co-Sponsor dieses Gewinnspiels auf, da GazetaBitcoin die Regeln mit gesponsort hat. Jeder teilnahmeberechtigte Account darf 2 Nummern für dieses Gewinnspiel nominieren. Nummern, die bereits getippt wurden, können nicht doppelt belegt werden. Es dürfen nur Accounts an diesem Gewinnspiel teilnehmen, die vor dem 12.09.2022 erstellt wurden. Um Schummeleien einzugrenzen, muss euer Account zum Zeitpunkt eurer Tippabgabe mindestens 15 verdientes Merit haben. Airdrop-Merit zählt nicht. Ich reserviere mir das Recht, neue oder verdächtige Accounts ohne Begründung abzulehnen. Ihr dürft nicht von GazetaBitcoin oder mir (1miau) gedistrustet sein. Accounts von GazetaBitcoin’s oder meiner (1miau) Distrustliste haben keine Erlaubnis, an diesem Gewinnspiel teilzunehmen. Ein Account pro Person, bitte seid ehrlich. Wenn jemand dagegen verstößt und ich finde es heraus, dann bekommt er und sein Alt auch bei richtig geratener Nummer kein wertvolles BTC, sondern negativen Trust. Ausgezahlt wird das BTC frühestens am 02.01.2023, wenn ich die Bitcoinadressen von euch habe. Das Hardware-Wallet wird nach Rücksprache des Gewinners mit betnomi von betnomi versandt. Teilnahmefrist ist bis 30.12.2022 um 23.59.59 MESZ. Formfehler führen zu Ausschluss. Teilnahme durch Ausfüllen des Codes: Code:Bitcointalk-Nutzername: 1. Tipp: 2. Tipp: Beiträge mit Tippabgaben dürfen nicht editiert werden, sonst werden sie abgelehnt. Das, was ich in die Liste aufnehme, gilt als gesetzt, also überlegt gut! Gewinn: 1. Platz: Hardwarewallet von Betnomi + 0,5 mBTC von 1miau + eine BitcoinRomania-Karte von GazetaBitcoin Zudem gibt es eine weitere Karte von GazetaBitcoin, welche durch die nachfolgenden, bis zu 3 Blöcke ermittelt wird. Für die ersten 9 Plätze gibt es jeweils eine 5$ Freiwette auf Betnomi. Viel Glück an alle!  In diesem Faden gelten die allgemein anerkannten Regeln. Gesponsort von",
  "score": 0,
  "upvotes": 0,
  "downvotes": 0,
  "url": "https://bitcointalk.org/index.php?topic=5415416",
  "comments": [
    {
      "author": "1miau",
      "created_time": "September 29, 2022, 10:06:31 PMLast edit: November 30, 2022, 11:02:08 PM by 1miau",
      "body": "Die gewählten Nummern: NummerBitcointalk-Nutzername_________________________________________________00. xandry01. xandry02. GazetaBitcoin03. IonCreanga04. Begru05. 5tift06. 07. haloxon08. Buchi-8809. Real-Duke10. Betwrong11. Betwrong12. Pmalek13. HeRetiK14. mole081515. IonCreanga16. NeuroticFish17. satscraper18. igor7219. gbianchi20. 21. TheNewcomer22. Prova12323. satscraper24. bullrun2020bro25. bullrun2020bro26. mole081527. Pmalek28. hymperion29. LTU_btc30. 31. Bongline32. citb0in33. Prova12334. cygan35. 36. -doubleU-37. 38. Ratimov39. joker_josue40. Mauser41. 42. babo43. cygan44. willi997445. 46. fillippone47. GazetaBitcoin48. bitbollo49. 50. TheNewcomer51. gbianchi52. 53. 54. 55. 5tift56. LTU_btc57. 58. Bongline59. 60. joker_josue61. 62. 63. fillippone64. NeuroticFish65. HeRetiK66. sam0067. hymperion68. 69. sam0070. 71. -doubleU-72. Ratimov73. 74. willi997475. 76. citb0in77. Begru78. 79. 80. Mauser81. 82. igor7283. haloxon84. 85. 86. CoinEraser87. 88. Buchi-8889. 90. babo91. bitbollo92. 93. 94. 95. 96. CoinEraser97. mv198698. mv198699. Real-Duke",
      "score": 0,
      "upvotes": 0,
      "downvotes": 0
    },
    {
      "author": "willi9974",
      "created_time": "September 30, 2022, 05:18:00 AM",
      "body": "Danke für das coole Gewinnspiel Code:Bitcointalk-Nutzername: willi99741. Tipp: 442. Tipp: 74",
      "score": 0,
      "upvotes": 0,
      "downvotes": 0
    },
    {
      "author": "mole0815",
      "created_time": "September 30, 2022, 07:01:16 AM",
      "body": "Schöne Sache danke.Da mir das Ding bei der letzten Verlosung im englischen Bereich schon durch die Lappen ging versuche ich mein Glück nun hier nochmal.Damals gab es eine Frage von sam00 die leider unbeantwortet blieb.Handelt es sich bei dem Ledger um einen Nano aus dem https://www.ledger.com/co-branded-partnership Shop?Vielleicht können wir das nun noch hier aufklären Code:Bitcointalk-Nutzername: mole08151. Tipp: 142. Tipp: 26",
      "score": 0,
      "upvotes": 0,
      "downvotes": 0
    },
    {
      "author": "Buchi-88",
      "created_time": "September 30, 2022, 07:09:24 AM",
      "body": "Danke für das Gewinnspiel an alle Ausführenden und Sponsoren  Code:Bitcointalk-Nutzername: Buchi-881. Tipp: 082. Tipp: 88",
      "score": 0,
      "upvotes": 0,
      "downvotes": 0
    },
    {
      "author": "Streissi",
      "created_time": "September 30, 2022, 07:19:08 AM",
      "body": "Nachtrag da editieren ja nicht erlaubt ist Code:Bitcointalk-Nutzername: Streissi1. Tipp: 022. Tipp: 42",
      "score": 0,
      "upvotes": 0,
      "downvotes": 0
    },
    {
      "author": "5tift",
      "created_time": "September 30, 2022, 07:22:00 AM",
      "body": "Auch von mir vielen Dank für für Deinen/Euren Einsatz  Code:Bitcointalk-Nutzername: 5tift1. Tipp: 05 2. Tipp: 55Ich wünsche ein schönes Wochenende allen zusammen.",
      "score": 0,
      "upvotes": 0,
      "downvotes": 0
    },
    {
      "author": "Pmalek",
      "created_time": "September 30, 2022, 07:26:49 AM",
      "body": "Code:Bitcointalk-Nutzername: Pmalek1. Tipp: 122. Tipp: 27Danke",
      "score": 0,
      "upvotes": 0,
      "downvotes": 0
    },
    {
      "author": "HeRetiK",
      "created_time": "September 30, 2022, 07:42:17 AM",
      "body": "Code:Bitcointalk-Nutzername: HeRetiK1. Tipp: 132. Tipp: 65Viel Glück allen und Danke für das Gewinnspiel!",
      "score": 0,
      "upvotes": 0,
      "downvotes": 0
    },
    {
      "author": "Real-Duke",
      "created_time": "September 30, 2022, 07:45:22 AM",
      "body": "Juhu, da bin ich doch auch gerne mit dabei Code:Bitcointalk-Nutzername: Rea-Duke1. Tipp: 092. Tipp: 99Danke an 1miau und Betnomi dafür",
      "score": 0,
      "upvotes": 0,
      "downvotes": 0
    },
    {
      "author": "citb0in",
      "created_time": "September 30, 2022, 08:47:48 AMLast edit: September 30, 2022, 10:55:13 AM by citb0in",
      "body": "Code:Bitcointalk-Nutzername: citb0in1. Tipp: 322. Tipp: 76",
      "score": 0,
      "upvotes": 0,
      "downvotes": 0
    },
    {
      "author": "CoinEraser",
      "created_time": "September 30, 2022, 09:03:07 AM",
      "body": "Dankeschön an 1miau, Betnomi, GazetaBitcoin und icopress für dieses schöne Gewinnspiel. Bei so einem tollen Preis mache ich doch gerne mit.  Code:Bitcointalk-Nutzername: CoinEraser1. Tipp: 862. Tipp: 96",
      "score": 0,
      "upvotes": 0,
      "downvotes": 0
    },
    {
      "author": "xandry",
      "created_time": "September 30, 2022, 10:10:43 AM",
      "body": "Dieses Angebot gilt nur für Einwohner Deutschlands, oder?Ich entschuldige mich für die Verwendung des Software-Übersetzers.",
      "score": 0,
      "upvotes": 0,
      "downvotes": 0
    },
    {
      "author": "cygan",
      "created_time": "September 30, 2022, 11:13:11 AM",
      "body": "Code:Bitcointalk-Nutzername: cygan1. Tipp: 342. Tipp: 43dank dir!",
      "score": 0,
      "upvotes": 0,
      "downvotes": 0
    },
    {
      "author": "mole0815",
      "created_time": "September 30, 2022, 12:51:12 PM",
      "body": "Quote from: xandry on September 30, 2022, 10:10:43 AMDieses Angebot gilt nur für Einwohner Deutschlands, oder?Ich entschuldige mich für die Verwendung des Software-Übersetzers.Es gibt ein paar Regeln die im ersten Beitrag zu finden sind aber das Land bzw. der Wohnort gehören nicht dazu Also wie ich das sehe kannst du hier gerne teilnehmen xandry",
      "score": 0,
      "upvotes": 0,
      "downvotes": 0
    },
    {
      "author": "xandry",
      "created_time": "September 30, 2022, 12:55:14 PM",
      "body": "Code:Bitcointalk-Nutzername: xandry1. Tipp: 002. Tipp: 01",
      "score": 0,
      "upvotes": 0,
      "downvotes": 0
    },
    {
      "author": "betnomi",
      "created_time": "September 30, 2022, 02:30:02 PM",
      "body": "1miau, GazetaBitcoin, icopress, thank you for organizing this wonderful contest!If you don't mind, we would like to add some Bitcoins to the fund of this contest!",
      "score": 0,
      "upvotes": 0,
      "downvotes": 0
    },
    {
      "author": "sam00",
      "created_time": "September 30, 2022, 07:04:03 PM",
      "body": "Quote from: 1miau on September 29, 2022, 10:06:18 PM~~~Vielen Dank @1miau @betnomi @GazetaBitcoin @icopress für ein weiteres interessantes Gewinnspiel mit grandiosen Preisen. Einen Ledger und oben drauf noch 0,5mBTC sind schonmal eine Hausnummer und jetzt wo:Quote from: betnomi on September 30, 2022, 02:30:02 PMIf you don't mind, we would like to add some Bitcoins to the fund of this contest!Betnomi sogar noch Bitcoins dazu steuern möchte, kann jeder wirklich nur wieder die Daumen drücken an Silvester. Bald platzen unsere Geldbörsen noch über von den ganzen von Betnomi bereitgestellten Bitcoins Ich gebe meinen Tipp schon einmal ab, da sich an der Wahrscheinlichkeit sowieso nichts ändern wird:Code:Bitcointalk-Nutzername: sam001. Tipp: 662. Tipp: 69",
      "score": 0,
      "upvotes": 0,
      "downvotes": 0
    },
    {
      "author": "1miau",
      "created_time": "September 30, 2022, 11:21:43 PM",
      "body": "Quote from: mole0815 on September 30, 2022, 07:01:16 AMDamals gab es eine Frage von sam00 die leider unbeantwortet blieb.Handelt es sich bei dem Ledger um einen Nano aus dem https://www.ledger.com/co-branded-partnership Shop?Vielleicht können wir das nun noch hier aufklären Da sich betnomi vermutlich nicht alle Beiträge übersetzen wird, würde ich betnomi einfach eine Nachricht senden und die Antwort teile ich dann hier mit. Dann sollten wir das geklärt bekommen.  Quote from: Streissi on September 30, 2022, 07:19:08 AMNachtrag da editieren ja nicht erlaubt ist Code:Bitcointalk-Nutzername: Streissi1. Tipp: 022. Tipp: 42Leider kann ich dich (noch) nicht in die Liste aufnehmen, weil laut Regeln zur Teilnahme 15 verdientes Merit benötigt werden. Du hast aktuell 5 Stück aber ich würde dir die Chance geben, bis zum Ende des Gewinnspiels die restlichen 10 Merits zu sammeln und dafür sind ja noch 3 Monate Zeit.  Dann würde ich dich mit in die Liste aufnehmen können. Quote from: mole0815 on September 30, 2022, 12:51:12 PMQuote from: xandry on September 30, 2022, 10:10:43 AMDieses Angebot gilt nur für Einwohner Deutschlands, oder?Ich entschuldige mich für die Verwendung des Software-Übersetzers.Es gibt ein paar Regeln die im ersten Beitrag zu finden sind aber das Land bzw. der Wohnort gehören nicht dazu Genau, es kann jeder teilnehmen, der die Regeln erfüllt. Aus welchem Land man kommt, gehört nicht dazu.  Quote from: betnomi on September 30, 2022, 02:30:02 PM1miau, GazetaBitcoin, icopress, thank you for organizing this wonderful contest!If you don't mind, we would like to add some Bitcoins to the fund of this contest!Vielen Dank, das ist wirklich sehr großzügig von euch!   Nachdem ihr schon beim vorigen Gewinnspiel eines an wertvollem BTC hinzugegeben habt, ist das natürlich noch einmal größer wertzuschätzen. Danke vielmals!  Bis hierhin sind alle Tipps eingetragen.",
      "score": 0,
      "upvotes": 0,
      "downvotes": 0
    },
    {
      "author": "GazetaBitcoin",
      "created_time": "October 01, 2022, 06:23:07 AM",
      "body": "Code:Bitcointalk-Nutzername: GazetaBitcoin1. Tipp: 022. Tipp: 47Danke 1miau, icopress und Betnomi!",
      "score": 0,
      "upvotes": 0,
      "downvotes": 0
    }
  ]
}