{
  "id": "topic_5412590",
  "title": "newnft",
  "author": "newnft",
  "created_time": "September 06, 2022, 12:17:53 PM",
  "content": "Selling Coinzilla verified accountpm me",
  "score": 0,
  "upvotes": 0,
  "downvotes": 0,
  "url": "https://bitcointalk.org/index.php?topic=5412590",
  "comments": [
    {
      "author": "cryptotelegramgroups",
      "created_time": "September 10, 2022, 04:03:30 PM",
      "body": "What’s the reason to buy it ?",
      "score": 0,
      "upvotes": 0,
      "downvotes": 0
    },
    {
      "author": "newnft",
      "created_time": "September 11, 2022, 04:42:47 PM",
      "body": "optimized for NFT",
      "score": 0,
      "upvotes": 0,
      "downvotes": 0
    },
    {
      "author": "adzkiy",
      "created_time": "February 18, 2023, 09:24:19 AMLast edit: February 18, 2023, 09:48:32 AM by adzkiy",
      "body": "Hi i need this, pm me (i cant pm you right now)",
      "score": 0,
      "upvotes": 0,
      "downvotes": 0
    },
    {
      "author": "bitjamz",
      "created_time": "June 22, 2023, 03:58:56 PM",
      "body": "way to late but you still have it? up sale?",
      "score": 0,
      "upvotes": 0,
      "downvotes": 0
    }
  ]
}