{
  "id": "topic_5424970",
  "title": "LiloBee",
  "author": "LiloBee",
  "created_time": "December 01, 2022, 09:25:58 AMLast edit: December 01, 2022, 11:11:55 AM by LiloBee",
  "content": "GamerHub is a multi-chain Crypto Game Aggregator for metaverses, Games, Guilds and NFTs. View us as the 1inch of the Crypto Gaming Industry. GamerHub makes it easy for Gamers to have access, discover and play different games on different blockchains all together under one roof. No boundaries, no-hassle, pure entertainment. GamerHub aims to be an ecosystem playing the role of Google Play Store or App Store for mobile applications, which will always remain relevant to the mobile market. Similarly, GamerHub acts as the gateway to a wide selection of play-to-earn gaming options, thus expanding our relevant audience to all blockchain-based players — a population that has been growing exponentially over recent years.Bounty Campaign starts from  1st December and will run 8 weekWeek 1: 01/12/2022 - 07/12/2022Week 2: 08/12/2022 - 14/12/2022Week 3: 15/12/2022 - 21/12/2022Week 4: 22/12/2022 - 28/12/2022Week 5: 29/12/2022 - 04/01/2023Week 6: 05/01/2022 - 11/01/2023Week 7: 12/01/2023 - 18/01/2023Week 8: 19/01/2023 - 25/01/2023Total Pool: 10,000$ worth of $GHT tokenDistribution: 1 Month After Bounty finished Pool InformationTwitter campaign - 35%Telegram campaign - 30%Article campaign - 25%YouTube campaign - 10%This Campaign will be managed by LBeeservice . To ask all the questions please join the Bounty group LBeeserviceGeneral Rules 1. Must join GamerHub Telegram Chat2. For any kind of bounty issue only ask in Bounty Group LBeeservice3. Must subscribe YouTube4. Every week you need to make a new post in the thread for weekly report submit, don’t edit and quote the previous post.5.  If you edit any previous post for report submitting your rewards will be Zero.6.  Don't complete any task just in one day. Do it by the whole week.7.  Using Multi-accounts, Spamming and Cheating are not allowed and will result in Disqualification from the Campaign.8.  Cheating Twitter Follower and Facebook Friends, using someone else to do the work and spamming or any kind of unethical behavior when participating to one of the campaigns are not allowed and will get you disqualified from all bounties.9. Submit the proof of authentication in the thread whatever campaign you are participating. It is a mandatory option.10. When bounty ends, you will have 7 days for any questions/complaints11. Making your own post must be unique and creative, useless and copy-paste posts are not allowed getting stakes12. Don’t discuss Bounty Related issue in Official Telegram Group  #PROOF OF REGISTRATIONForum Username: Forum Profile Link: Telegram Username: Participated Campaigns: BSC Wallet Address: TWITTER CAMPAIGNRULES1. Follow GamerHub Twitter Account 2. Your Twitter account must have at least 500 real followers.3. Your Twitter audit score must be equal to at least 90% and only real followers from the last audit will count.4. Your weekly posts must be at least 30 characters long, and unique. If you are found out literally copy-pasting other users posts, you will not be awarded any stakes, be unique.5. Participant profile must be public.6. All tasks should be done Daily, using 1-4 days to complete tasks will result to no stake for the week. 7. Use this Hashtags on your Tweet and Retweet : #GamerHub #IDO $GHT #NFTs #GameFi #Metaverse @Gamer_hub_io and Website link.REWARDS5 Valid Tweets, Retweets and likes per week = 5 Stakes/week8 Valid Tweets, Retweets and likes per week = 8 Stakes/week10 Valid Tweets, Retweets and likes per week = 10 Stakes/week       TELEGRAM CAMPAIGNRULES1. You Must join GamerHub TELEGRAM And TELEGRAM BOUNTY2. Add  “GamerHub Ambassador” to your Telegram username and Add Avatar3. Stay in the Telegram group until the Bounty is over.4. Anyone Posting Bounty Related issue in The GamerHub Official Group will be Disqualified From All campaign5. Promote GamerHub in other Telegram groups, but they need to be made in a constructive way, not in a way that might be considered spamming. Deleted messages won’t be counted.REWARDS1. Join Telegram Group = 1 Stake2. Add  “GamerHub Ambassador” to your Telegram username = 1 stake3. Using GamerHub Avatar in Telegram  = 1 Stakes4. Posting messages about GamerHub in your Telegram group or Others (minimum 1,000 members)( Use Project Telegram handle and website link) : 1 stakes per approved post5. Actively Discuss on main Telegram about their Recent tropic( Don’t use hashtag on post and try to make conversation): 1 stakes per approved post6. Make 2 Post on main group and Maximum 5 post on others group Per Week.       ARTICLE CAMPAIGNRULES1. Articles should be original and unique with a minimum of 500 words.2. Don't copy website about us section, details and whitepaper and other official staffs. Create your own words.3. Article founds plagiarized will get 0 stakes.4. Only 1 article per person. You can use your own blog website or medium, Steemit.5. Article topic must be about the Project.6. Article must contain 2 images related the project, link to the Website, telegram group.7. You must put your proof of authentication on the bottom of the article.REWARDSHigh Quality: 80 stakesMedium Quality: 40 stakesLow Quality: 20 stakes       YOUTUBE CAMPAIGNRULES1. Video must be original and made only by you.2. Your video must be 3 min long and must be uploaded to Youtube.3. Your video must have 300 views minimum. Or it will be disqualified.4. Only one video per person is allowed.5. Video description must have the website link, telegram group link.6. You must put your proof of authentication on the bottom of the video description.REWARDSHigh Quality: 80 stakesMedium Quality: 40 stakesLow Quality: 20 stakes       Note: I am not a part of the team, I was hired as a bounty manager to manage their bounty. Please join on your own risk, and if you want to invest please do your own research. I did my research too but I can be wrong.",
  "score": 0,
  "upvotes": 0,
  "downvotes": 0,
  "url": "https://bitcointalk.org/index.php?topic=5424970",
  "comments": [
    {
      "author": "LiloBee",
      "created_time": "December 01, 2022, 09:26:40 AM",
      "body": "Reserved for update",
      "score": 0,
      "upvotes": 0,
      "downvotes": 0
    },
    {
      "author": "khokaboss999",
      "created_time": "December 01, 2022, 09:27:29 AM",
      "body": "#PROOF OF REGISTRATIONForum Username: khokaboss999Forum Profile Link: https://bitcointalk.org/index.php?action=profile;u=3377711Telegram Username: @majedur12Participated Campaigns: Twitter BSC Address:0xEe673bC4da6764D6166c17355CcDdC4FA2BDBE37",
      "score": 0,
      "upvotes": 0,
      "downvotes": 0
    },
    {
      "author": "Adhora1",
      "created_time": "December 01, 2022, 09:27:50 AM",
      "body": "#PROOF OF REGISTRATIONForum Username: Adhora1Forum Profile Link: https://bitcointalk.org/index.php?action=profile;u=3453804Telegram Username:@Faria109Participated Campaigns: Twitter, telegram, Facebook, Discord, Reddit,BSC wallet address: 0x2ea89c40Eced95e2cD43457d3bDbCb8Faf40f353",
      "score": 0,
      "upvotes": 0,
      "downvotes": 0
    },
    {
      "author": "S01819642984",
      "created_time": "December 01, 2022, 09:28:43 AM",
      "body": "Reserved",
      "score": 0,
      "upvotes": 0,
      "downvotes": 0
    },
    {
      "author": "afjal010",
      "created_time": "December 01, 2022, 09:29:37 AM",
      "body": "PROOF OF REGISJTRATIONForum Username: afjal010Forum Profile Link: https://bitcointalk.org/index.php?action=profile;u=3512840Telegram Username: @bafjalParticipated Campaign: Twitter, Telegram Instagram, Facebook, LinkedIn BSC Wallet Address: 0x51c53cF67fC1507EBbaa58b95cc66192C3c4bc3E",
      "score": 0,
      "upvotes": 0,
      "downvotes": 0
    },
    {
      "author": "Dudu2.0",
      "created_time": "December 01, 2022, 09:31:00 AM",
      "body": "#Proof Of RegistrationForum Username: Dudu2.0Forum Profile Link: https://bitcointalk.org/index.php?action=profile;u=3369729Telegram Username: @Dudu2_0Participated Campaigns: Twitter, Telegram, Discord, Facebook, MediumBSC Wallet Address: 0x765e00E12C9e4F91f1494FDF01f3b2C16adDE2eB",
      "score": 0,
      "upvotes": 0,
      "downvotes": 0
    },
    {
      "author": "Anderson7.9",
      "created_time": "December 01, 2022, 09:31:13 AM",
      "body": "#PROOF OF REGISTRATIONForum Username: Anderson7.9Forum Profile Link: https://bitcointalk.org/index.php?action=profile;u=3456943Telegram Username: @deskat6778Participated Campaigns:  Twittter,TelegramBSC wallet  Address : 0x1228b2C5C9FA5f2Bd8c0F5CCD7DEd70189a72B6a",
      "score": 0,
      "upvotes": 0,
      "downvotes": 0
    },
    {
      "author": "Fatemafh",
      "created_time": "December 01, 2022, 09:31:21 AM",
      "body": "PROOF OF AUTHENTICATIONBitcoin username: FatemafhEmail: ayesha907ayesha@gmail.comBitcoin Profile link:https://bitcointalk.org/index.php?action=profile;u=3462361Twitter username: fatemahasan907 Twitter Profile link: https://twitter.com/fatemahasan907?t=TL4zvvZI16LWlyQ2bNwOtg&s=09Telegram Username: @ritu907907Telegram Profile link:https://t.me/ritu907907Facebook username: @ritu907907Facebook profile link:https://www.facebook.com/ritu907907 Bsc Wallet address:0x834A7111970b48dF22F7addA3eF81df3c9AEcD03",
      "score": 0,
      "upvotes": 0,
      "downvotes": 0
    },
    {
      "author": "Battery Low",
      "created_time": "December 01, 2022, 09:32:04 AM",
      "body": "#Proof of Registration Bitcointalk Username: Battery LowBitcointalk Profile Link: https://bitcointalk.org/index.php?action=profile;u=3468918Telegram Username: @batterlowrajuParticipated Campaigns: Twitter, Facebook, LinkedIn, Telegram, DiscordBinance Smart Chain (BSC/BEP20) Wallet Address: 0xf0fA2ed2D5fDBbf4b41b474a007FB6c4c245C432",
      "score": 0,
      "upvotes": 0,
      "downvotes": 0
    },
    {
      "author": "SSC.2K22",
      "created_time": "December 01, 2022, 09:32:08 AM",
      "body": "PROOF OF AUTHENTICATIONBitcoin username: SSC.2K22Email:ayeshasiddika10241024@gmail.comBitcoin profile link: https://bitcointalk.org/index.php?action=profile;u=3459446Twitter username:@asha907907Twitter profile link:https://twitter.com/asha907907?t=09Telegram Username: @VangaghorTelegram profile link: https://t.me/VangaghorFacebook profile link:https://www.facebook.com/profile.php?id=100078955612786Bsc Wallet address:0x16bcD965D57919d575573F330663fd50357B1BA3Twitter audit link:https://www.twitteraudit.com/asha907907Discord username: @asha907907#7882",
      "score": 0,
      "upvotes": 0,
      "downvotes": 0
    },
    {
      "author": "Gegorjohan76",
      "created_time": "December 01, 2022, 09:32:24 AM",
      "body": "#PROOF OF REGISTRATIONForum Username: Gegorjohan76Forum Profile Link: https://bitcointalk.org/index.php?action=profile;u=3430536;sa=summaryTelegram Username: @Nusrat1510Participated Campaigns: Twitter, Telegram, Facebook, Discord, Tiktok, Instagram BSC Wallet Address: 0x8ac77B81950B81E50d17962EE9E7f895Cb46a7C8",
      "score": 0,
      "upvotes": 0,
      "downvotes": 0
    },
    {
      "author": "Swieetboyhood66",
      "created_time": "December 01, 2022, 09:32:31 AM",
      "body": "#PROOF OF REGISTRATIONForum Username: Swieetboyhood66Forum Profile Link: https://bitcointalk.org/index.php?action=profile;u=3485672Telegram Username: @Rubelrana6678Participated Campaigns:  Twitter,Telegram BSC wallet address : 0xebA0A47d171C0cf1277cC97696A33f3117851aCb",
      "score": 0,
      "upvotes": 0,
      "downvotes": 0
    },
    {
      "author": "Hasan@32",
      "created_time": "December 01, 2022, 09:33:12 AMLast edit: December 01, 2022, 10:50:31 AM by Hasan@32",
      "body": "Poof of registrationForum username: Hasan@32Forum profile link: https://bitcointalk.org/index.php?action=profile;u=3510981Telegram username: @nusrat44Prticipating campaign : Twitter, Facebook, Instagram, linked BSC WALLET ADDRESS: 0xAC9cb66AAC2A460DE44Dec231A18a092C0EF9B30",
      "score": 0,
      "upvotes": 0,
      "downvotes": 0
    },
    {
      "author": "Listena2",
      "created_time": "December 01, 2022, 09:33:21 AM",
      "body": "#PROOF OF REGISTRATIONForum Username: Listena2Forum Profile Link : https://bitcointalk.org/index.php?action=profile;u=3505684Telegram Username: @mariya685Participated Campaigns:Twitter,  Facebook. and telegram.BEP-20 Wallet Address0xFe4798a0AAC64fE24543c0B6a48ecB4b1C727f5e",
      "score": 0,
      "upvotes": 0,
      "downvotes": 0
    },
    {
      "author": "Sobuz001",
      "created_time": "December 01, 2022, 09:33:27 AM",
      "body": "Poof of registrationForum username: sobuz001Forum profile link: https://bitcointalk.org/index.php?action=profile;u=3515643Telegram username: @Hridoy_0001Prticipating campaign : Twitter, Facebook, Instagram, linked BSC WALLET ADDRESS:- 0x3f3a09ba68A82F0eBFac1005aD9F5710CEA0c03B",
      "score": 0,
      "upvotes": 0,
      "downvotes": 0
    },
    {
      "author": "White.444",
      "created_time": "December 01, 2022, 09:35:35 AM",
      "body": "#PROOF OF REGISTRATIONForum Username: White.444Forum Profile Link: https://bitcointalk.org/index.php?action=profile;u=3389222Telegram username: @White4443Campaigns applied: Twitter,Telegram,Facebook,Tik tokBSC wallet address: 0x3239171c8a8cBc0519743C63409b096Ed1D54B6B",
      "score": 0,
      "upvotes": 0,
      "downvotes": 0
    },
    {
      "author": "Adewumi25",
      "created_time": "December 01, 2022, 09:35:47 AM",
      "body": "#PROOF OF REGISTRATIONForum Username: Adewumi25 Forum Profile Link: https://bitcointalk.org/index.php?action=profile;u=3452195Telegram Username: @adewumi1996 Participated Campaigns: Twitter BSC Wallet Address: 0x1e64894CA0423F3d93bB06795275befA66c74067",
      "score": 0,
      "upvotes": 0,
      "downvotes": 0
    },
    {
      "author": "Biology56",
      "created_time": "December 01, 2022, 09:36:04 AM",
      "body": "#PROOF OF REGISTRATIONForum Username: Biology56Forum Profile Link: https://bitcointalk.org/index.php?action=profile;u=3479060;Telegram Username: @Biology147Participated Campaigns: Twitter, Telegram, Facebook, Tiktok BSC Wallet Address: 0x771b5F676786Bb2072F0574F6c17551B57c369fE",
      "score": 0,
      "upvotes": 0,
      "downvotes": 0
    },
    {
      "author": "Curatorial",
      "created_time": "December 01, 2022, 09:36:33 AM",
      "body": "#PROOF OF REGISTRATIONForum Username: CuratorialForum Profile Link: https://bitcointalk.org/index.php?action=profile;u=3450186Telegram Username: @Mim1367Participated Campaigns:  Twitter,Telegram,aritcle BSC wallet address : 0xAc2d456B537f46651874013888E0AfcD9D9c7a23",
      "score": 0,
      "upvotes": 0,
      "downvotes": 0
    }
  ]
}