{
  "id": "topic_5441423",
  "title": "bonfire66",
  "author": "bonfire66",
  "created_time": "February 27, 2023, 02:33:42 PM",
  "content": "Кто-нибудь из читающих данный текст вообще читал когда-нибудь книги Джека Лондона? Нет? А зря. ИМХО – лучший американский писатель всех времен. И у Лондона в библиографии есть один особый роман, который стоит несколько особняком. «Мартин Иден» Почему? А потому что он - автобиографический. Отчасти. Но очень сильный. А почему он мне так нравится? Ну… на самом деле он мне нравился всегда, но сейчас это произведение особенно похоже на мою войну с текущей реальностью, например с интернетом, ютюбом, троллями, хейтерами и прочими платформами для публикации контента. Я продолжаю упорно делать свою работу. Публикую ролики, вот уже свыше 250 штук. Публикую посты, ответы, статьи или тексты. А вот гугл поддается моему напору весьма  вяло и скучно. Иногда вдруг начинает легкую поддержку того или другого ролика или поста…  а потом сдыхает. Суть того романа Лондона в том, что его герой упорно и упрямо шел к своей цели: стать великим писателем и заработать много денег. Не смотря ни на что. И он им стал. В конце концов. А потом утоп в море.        И я тоже, почти как и Мартин Иден, в конце концов, рано или поздно стану великим блоггером с миллионами подписчиков. Но утонуть пока не хочу. Потому что упрямства и стойкости у меня не занимать. Что бы не случилось, мировые катастрофы, третьи мировые воины, финансовые коллапсы, землетрясения или наводнения – я все равно буду делать свое дело. Вне зависимости, буду ли я получать за это деньги. Мне проще, чем герою Джека Лондона – деньги у меня УЖЕ есть, и их мне не нужно зарабатывать тяжким трудом. Но я хочу больше денег, ибо они дают свободу, а также признание мирового сообщества на старости лет. Да, немного призвания у меня уже есть в наличии, как и денег, но хочется еще немного больше, особенно денег. Затем и стараюсь!",
  "score": 0,
  "upvotes": 0,
  "downvotes": 0,
  "url": "https://bitcointalk.org/index.php?topic=5441423",
  "comments": [
    {
      "author": "talli_t",
      "created_time": "March 06, 2023, 03:53:34 PM",
      "body": "как раз на днях приобрел данную книгу) вы еще раз натолкнули на прочтение",
      "score": 0,
      "upvotes": 0,
      "downvotes": 0
    },
    {
      "author": "bonfire66",
      "created_time": "March 06, 2023, 04:19:04 PM",
      "body": "После того, как прочтете именно эту книгу, рекомендую тут же для контраста прочитать \"как бы оригинал\" жизнеописания Джека Лондона Ирвинга Стоуна \"Моряк в Седле\". Прям настоятельно  рекомендую прочитать эти книги одну за другой и сравнить!",
      "score": 0,
      "upvotes": 0,
      "downvotes": 0
    }
  ]
}